rouge_mongolian/__init__.py
rouge_mongolian/rouge.py
rouge_mongolian/rouge_score.py
rouge_mongolian-1.0.3.dist-info/LICENSE
rouge_mongolian-1.0.3.dist-info/METADATA
rouge_mongolian-1.0.3.dist-info/WHEEL
rouge_mongolian-1.0.3.dist-info/top_level.txt
rouge_mongolian-1.0.3.dist-info/RECORD
