Metadata-Version: 2.1
Name: rouge-mongolian
Version: 1.0.3
Summary: 蒙古文ROUGE评价工具
Author: IMNU Han Yongshun
Author-email: hys971030@163.com
License: MIT
Keywords: python,rouge,mongolian,windows,mac,linux
License-File: LICENSE
Requires-Dist: six >=1.16.0
